nython/__init__.py
nython/nythonize.py
nython-0.1.1.dist-info/LICENSE
nython-0.1.1.dist-info/WHEEL
nython-0.1.1.dist-info/METADATA
nython-0.1.1.dist-info/RECORD
