Metadata-Version: 2.1
Name: nython
Version: 0.1.1
Summary: Seamless Nim extension modules for Python
Home-page: https://github.com/sstadick/nython
License: MIT
Keywords: nim,extension
Author: Seth Stadick
Author-email: sstadick@gmail.com
Requires-Python: >=3.7,<4.0
Classifier: License :: OSI Approved :: MIT License
Classifier: Programming Language :: Python :: 3
Classifier: Programming Language :: Python :: 3.7
Classifier: Programming Language :: Python :: 3.8
Project-URL: Repository, https://github.com/sstadick/nython
